[
  {"model": "schools.classroom", "pk": 1, "fields": {"name": "روضة"}},
  {"model": "schools.classroom", "pk": 2, "fields": {"name": "الأساسي الأول"}},
  {"model": "schools.classroom", "pk": 3, "fields": {"name": "الأساسي الثاني"}},
  {"model": "schools.classroom", "pk": 4, "fields": {"name": "الأساسي الثالث"}},
  {"model": "schools.classroom", "pk": 5, "fields": {"name": "الأساسي الرابع"}},
  {"model": "schools.classroom", "pk": 6, "fields": {"name": "الأساسي الخامس"}},
  {"model": "schools.classroom", "pk": 7, "fields": {"name": "الأساسي السادس"}},
  {"model": "schools.classroom", "pk": 8, "fields": {"name": "الأساسي السابع"}},
  {"model": "schools.classroom", "pk": 9, "fields": {"name": "الأساسي الثامن"}},
  {"model": "schools.classroom", "pk": 10, "fields": {"name": "الأساسي التاسع"}},

  {"model": "schools.educationlevel", "pk": 1, "fields": {"name": "مستوى 1"}},
  {"model": "schools.educationlevel", "pk": 2, "fields": {"name": "مستوى 2"}},
  {"model": "schools.educationlevel", "pk": 3, "fields": {"name": "مستوى 3"}},
  {"model": "schools.educationlevel", "pk": 4, "fields": {"name": "مستوى 4"}},
  {"model": "schools.educationlevel", "pk": 5, "fields": {"name": "مستوى 5"}},
  {"model": "schools.educationlevel", "pk": 6, "fields": {"name": "مستوى 6"}},
  {"model": "schools.educationlevel", "pk": 7, "fields": {"name": "مستوى 7"}},
  {"model": "schools.educationlevel", "pk": 8, "fields": {"name": "مستوى 8"}},
  {"model": "schools.educationlevel", "pk": 9, "fields": {"name": "مستوى 9"}},

  {"model": "schools.classlevel", "pk": 1, "fields": {"name": "مستوى 1"}},
  {"model": "schools.classlevel", "pk": 2, "fields": {"name": "مستوى 2"}},
  {"model": "schools.classlevel", "pk": 3, "fields": {"name": "مستوى 3"}},
  {"model": "schools.classlevel", "pk": 4, "fields": {"name": "مستوى 4"}},
  {"model": "schools.classlevel", "pk": 5, "fields": {"name": "مستوى 5"}},
  {"model": "schools.classlevel", "pk": 6, "fields": {"name": "مستوى 6"}},
  {"model": "schools.classlevel", "pk": 7, "fields": {"name": "مستوى 7"}},
  {"model": "schools.classlevel", "pk": 8, "fields": {"name": "مستوى 8"}},
  {"model": "schools.classlevel", "pk": 9, "fields": {"name": "مستوى 9"}},
  {"model": "schools.classlevel", "pk": 9, "fields": {"name": "مستوى 9"}},
  {"model": "schools.classlevel", "pk": 9, "fields": {"name": "مستوى 9"}},
  {"model": "schools.classlevel", "pk": 9, "fields": {"name": "مستوى 9"}},
  {"model": "schools.classlevel", "pk": 9, "fields": {"name": "مستوى 9"}},
  {"model": "schools.classlevel", "pk": 9, "fields": {"name": "مستوى 9"}},
  {"model": "schools.classlevel", "pk": 9, "fields": {"name": "مستوى 9"}},
  {"model": "schools.classlevel", "pk": 9, "fields": {"name": "مستوى 9"}},
  {"model": "schools.classlevel", "pk": 9, "fields": {"name": "مستوى 9"}},
  {"model": "schools.classlevel", "pk": 9, "fields": {"name": "مستوى 9"}},
  {"model": "schools.classlevel", "pk": 9, "fields": {"name": "مستوى 9"}},
  {"model": "schools.classlevel", "pk": 9, "fields": {"name": "مستوى 9"}},
  {"model": "schools.classlevel", "pk": 9, "fields": {"name": "مستوى 9"}},
  {"model": "schools.classlevel", "pk": 9, "fields": {"name": "مستوى 9"}},
  {"model": "schools.classlevel", "pk": 9, "fields": {"name": "مستوى 9"}},
  {"model": "schools.classlevel", "pk": 9, "fields": {"name": "مستوى 9"}},
  {"model": "schools.classlevel", "pk": 9, "fields": {"name": "مستوى 9"}},
  {"model": "schools.classlevel", "pk": 9, "fields": {"name": "مستوى 9"}},
  {"model": "schools.classlevel", "pk": 9, "fields": {"name": "مستوى 9"}},
  {"model": "schools.classlevel", "pk": 9, "fields": {"name": "مستوى 9"}},
  {"model": "schools.classlevel", "pk": 9, "fields": {"name": "مستوى 9"}},
  {"model": "schools.classlevel", "pk": 9, "fields": {"name": "مستوى 9"}},
  {"model": "schools.classlevel", "pk": 9, "fields": {"name": "مستوى 9"}},

  {"model": "schools.section", "pk": 1, "fields": {"name": "أ"}},
  {"model": "schools.section", "pk": 2, "fields": {"name": "ب"}},
  {"model": "schools.section", "pk": 3, "fields": {"name": "ج"}},
  {"model": "schools.section", "pk": 4, "fields": {"name": "د"}},
  {"model": "schools.section", "pk": 5, "fields": {"name": "ه"}},
  {"model": "schools.section", "pk": 6, "fields": {"name": "و"}},
  {"model": "schools.section", "pk": 7, "fields": {"name": "ز"}},
  {"model": "schools.section", "pk": 8, "fields": {"name": "ح"}},
  {"model": "schools.section", "pk": 9, "fields": {"name": "ط"}},
  {"model": "schools.section", "pk": 10, "fields": {"name": "ي"}},
  {"model": "schools.section", "pk": 11, "fields": {"name": "ك"}},
  {"model": "schools.section", "pk": 12, "fields": {"name": "ل"}},
  {"model": "schools.section", "pk": 13, "fields": {"name": "م"}},
  {"model": "schools.section", "pk": 14, "fields": {"name": "ن"}},
  {"model": "schools.section", "pk": 15, "fields": {"name": "س"}},
  {"model": "schools.section", "pk": 16, "fields": {"name": "ع"}},
  {"model": "schools.section", "pk": 17, "fields": {"name": "ف"}},
  {"model": "schools.section", "pk": 18, "fields": {"name": "ص"}},
  {"model": "schools.section", "pk": 19, "fields": {"name": "ق"}},
  {"model": "schools.section", "pk": 20, "fields": {"name": "ر"}},
  {"model": "schools.section", "pk": 21, "fields": {"name": "ش"}},
  {"model": "schools.section", "pk": 22, "fields": {"name": "ت"}},
  {"model": "schools.section", "pk": 23, "fields": {"name": "خ"}},
  {"model": "schools.section", "pk": 24, "fields": {"name": "غ"}},
  {"model": "schools.section", "pk": 25, "fields": {"name": "ض"}},
  {"model": "schools.section", "pk": 26, "fields": {"name": "ظ"}},
  {"model": "schools.section", "pk": 27, "fields": {"name": "ذ"}}
]
